paho-stubs/__init__.pyi
paho-stubs/mqtt/__init__.pyi
paho-stubs/mqtt/client.pyi
paho-stubs/mqtt/matcher.pyi
paho-stubs/mqtt/packettypes.pyi
paho-stubs/mqtt/properties.pyi
paho-stubs/mqtt/publish.pyi
paho-stubs/mqtt/reasoncodes.pyi
paho-stubs/mqtt/subscribe.pyi
paho-stubs/mqtt/subscribeoptions.pyi
paho_mqtt_stubs-0.1.0.dist-info/WHEEL
paho_mqtt_stubs-0.1.0.dist-info/METADATA
paho_mqtt_stubs-0.1.0.dist-info/RECORD
